comtele_sdk/__init__.py
comtele_sdk/account_service.py
comtele_sdk/blacklist_service.py
comtele_sdk/contextmessage_service.py
comtele_sdk/credit_service.py
comtele_sdk/delivery_status.py
comtele_sdk/reply_service.py
comtele_sdk/report_group_type.py
comtele_sdk/textmessage_service.py
comtele_sdk-1.1.3.dist-info/METADATA
comtele_sdk-1.1.3.dist-info/RECORD
comtele_sdk-1.1.3.dist-info/WHEEL
comtele_sdk-1.1.3.dist-info/top_level.txt
services/__init__.py
services/account_service.py
services/contextmessage_service.py
services/credit_service.py
services/delivery_status.py
services/reply_service.py
services/report_group_type.py
services/textmessage_service.py
