Metadata-Version: 2.1
Name: comtele-sdk
Version: 1.1.3
Summary: SDK para envio de mensagens de texto usando a plataforma Comtele
Home-page: UNKNOWN
Author: Diego Vieira
Author-email: desenvolvimento@comtele.com.br
License: UNKNOWN
Keywords: sms,REST,comtele,phone,telephony
Platform: UNKNOWN
